{"title": "Những quy tắc để giàu có", "content": "Những quy tắc để giàu có Richard Templar Những quy tắc để giàu có Tóm tắt cuốn sách \"Những Quy Tắc Để Giàu Có\": Giống như khi đi tìm kho báu, để khởi đầu hành trình đến đích giàu có, bạn cũng cần một tấm bản đồ chi tiết, chính xác. Những quy tắc để làm giàu của tác giả Richard Templar chính là tấm bản đồ như thế. Trong cuốn sách này, Richard Templar sẽ dẫn dắt các bạn bắt đầu với Suy nghĩ giàu có để trở nên giàu có và giàu có hơn nữa rồi chia sẻ giàu có. Những quy tắc thiết thực, hữu ích, được đúc kết từ kinh nghiệm của rất nhiều người mà tác giả đưa ra sẽ giúp bạn ngày càng tiến gần đến đích. Hãy đọc, nghiền ngẫm kỹ từng quy tắc, và quan trọng nhất là hãy áp dụng chúng, bạn sẽ thấy điều kỳ diệu xảy ra.\nRichard Templar một lần nữa quay trở lại với chúng ta và lần này ông sẽ giúp các bạn làm giàu. Với phong cách viết hài hước, dễ hiểu độc đáo, Richard sẽ tiết lộ những nguyên tắc vàng nhưng rất đơn giản, dễ áp dụng để giúp bạn kiếm tiền và kiếm nhiều tiền hơn nữa.\nNhững quy tắc để giàu có phân tích thói quen, lối tư duy, phong cách và các bí quyết tài chính để bạn trở nên giàu có hơn, hạnh phúc hơn và thành công hơn.\nMời các bạn đón đọc cuốn sách \"Những Quy Tắc Để Giàu Có - Richard Templar\"", "detailLink": "https://waka.vn/nhung-quy-tac-de-giau-co-roGj1W.html?type=1", "thumpnail": "https://307a0e78.vws.vegacdn.vn/view/v2/image/img.book/0/0/0/2515.jpg?v=4&w=200&h=292"}