{"title": "Kinh doanh một cuộc chơi lớn", "content": "Kinh doanh một cuộc chơi lớn Nhiều tác giả Kinh doanh một cuộc chơi lớn Tóm tắt cuốn sách \"Kinh Doanh Một Cuộc Chơi Lớn\": The Great Game of Business đã được chọn là một trong 30 cuốn sách kinh doanh hay nhất của năm do Soundview Executive Book Summaries bình chọn.\nJack Stack tiếp quản Tập đoàn Springfield Remanufacturing (SRC) tại Springfield, Missouri vào đầu những năm 1980, khi tập đoàn này đang đứng trên bờ vực phá sản. Do trước đó hoạt động trong một lĩnh vực khá khác biệt, Stack không hề biết cách để “quản lý” một công ty. Bù lại, ông biết nguyên tắc chính của những cuộc thi đấu thể thao và dân chủ: giữ điểm số, cùng tận hưởng niềm vui, chơi công bằng, đưa ra các lựa chọn và có được tiếng nói của mình. Và Stack đã áp dụng những nguyên tắc này trong suốt quá trình vực dậy và phát triển SRC đi đến thành công như ngày hôm nay: Liên tục nằm trong danh sách 5000 công ty vừa và nhỏ phát triển nhất nước Mỹ theo tạp chí INC. bầu chọn.\nVới những nguyên lý này, Stack cũng đã tạo ra cách quản lý của riêng mình mang tên “Cuốn sách mở” với trọng tâm là: để cho tất cả nhân viên_cổ đông_ trong công ty tham gia vào mọi vấn đề của công ty, nhất là các quyết định về tài chính. Điều này khiến tất cả nhân viên của SRC đều hiểu và thấm nhuần: các nỗ lực của họ đều tác động trực tiếp lên chính thu nhập của họ.\nPhương pháp quản lý “Cuốn sách mở” được Stack đưa ra trong cuốn sách The Great Game of Business, một hệ thống mà như ông miêu tả, đơn thuần là một trò chơi, một phương pháp đơn giản mà ai cũng có thể thực hiện và áp dụng được vào thực tế.\nMời các bạn đón đọc cuốn sách \"Kinh Doanh Một Cuộc Chơi Lớn - Nhiều tác giả\"", "detailLink": "https://waka.vn/kinh-doanh-mot-cuoc-choi-lon-rjyzwW.html?type=1", "thumpnail": "https://307a0e78.vws.vegacdn.vn/view/v2/image/img.book/0/0/0/2322.jpg?v=2&w=200&h=292"}