{"title": "Nói với người bạn tu học", "content": "Nói với người bạn tu học Nguyễn Duy Nhiên Nói với người bạn tu học (Sách sẽ hết hạn vào ngày 31/12/2018, quý độc giả vui lòng đọc sách trước ngày 31/12/2018.)\nTóm tắt cuốn sách \"Nói Với Người Bạn Tu Học\":\nQuyển sách này đã được xuất bản trước đây với tựa đề Hạnh phúc và con đường tu học. Trong ấn bản mới này tác giả đã có những bài viết mới bổ sung.Nói với người bạn tu học gồm có 17 bài viết ngắn của tác giả nó giống lời nhắn nhủ nhẹ nhàng mà lại rất sâu sắc. Những bài viết như là lời giải đáp của tác giả dành cho những bạn mới tu học  giúp các bạn hiểu được cái bản chất cốt lõi, thực sự của Phật giáo. Hóa giải những hiểu lầm về Phật giáo thường gặp. Ví như hạnh phúc của con người là gì? Như thế nào để đạt được hạnh phúc? Sống trong thực tại và sống ở thực tại có gì khác nhau không? Đạo Phật làm cho một quốc gia không thể trở nên giàu có và phú cường, con người trở thành thụ động và yếm thế có phải chăng? Tu có phải là dẹp hết ham muốn không? Tu có phải là từ bỏ sự nghiệp, đi ngược lại với sự tiến bộ của xã hội? Tất cả sẽ được sáng tỏ, những điều bạn còn băn khoăn trăn trở khi muốn dứt bỏ những phiền muộn cuộc sống để tìm kiếm sự bình an trong tâm hồn?Và đặc biệt tác giả không chỉ đưa ra những vấn đề mà còn gợi mở cho chúng ta những hướng đi mà chính tác giả đã gặp và trải qua.\nMời các bạn đón đọc cuốn sách \"Nói Với Người Bạn Tu Học\"!", "detailLink": "https://waka.vn/noi-voi-nguoi-ban-tu-hoc-rlAAoW.html?type=1", "thumpnail": "https://307a0e78.vws.vegacdn.vn/view/v2/image/img.book/0/0/0/9908.jpg?v=2&w=200&h=292"}