{"title": "Thời gian trong mỗi bước chân", "content": "Thời gian trong mỗi bước chân Thủy Vũ Thời gian trong mỗi bước chân Tóm tắt sách \"Thời Gian Trong Mỗi Bước Chân\":\nVới phong cách viết nhẹ nhàng, lãng mạn quen thuộc, Thủy Vũ mang đến Thời Gian Trong Mỗi Bước Chân - một tuyển tập với những truyện ngắn hay, phản ánh nhiều mặt của tình yêu thời hiện đại. Họ lạc mất rồi tìm thấy, tìm thấy và lạc mất nhau,… Con người cứ rong ruổi trên con đường tình yêu đôi lúc như vô định của mình, và phải rất lâu họ mới nhận ra được mình cần phải làm gì?\nThủy Vũ từng là tác giả được nhiều độc giả yêu thích dưới bút danh Uyển. Thủy Vũ có phong cách viết nhẹ nhàng, mềm mại và đôi khi hơi thách đố người đọc, nhưng càng đọc Thủy Vũ thì người ta càng thấy một Thủy Vũ rất trí tuệ qua từng câu chữ.\nCác truyện của Thủy Vũ đều được đăng tải nhiều trên các trang truyện và hầu hết đều đón nhận được những phản hồi tích cực từ độc giả. Với phong cách viết này, truyện của Thủy Vũ cũng rất kén độc giả nhưng độc giả của cô có ở mọi lứa tuổi.\nWaka trân trọng giới thiệu sách Thời Gian Trong Mỗi Bước Chân.", "detailLink": "https://waka.vn/thoi-gian-trong-moi-buoc-chan-r1ygW.html?type=1", "thumpnail": "https://307a0e78.vws.vegacdn.vn/view/v2/image/img.book/0/0/0/1156.jpg?v=1&w=200&h=292"}