{"title": "Đọc sách như một nghệ thuật", "content": "Đọc sách như một nghệ thuật Mortimer J.Adler Đọc sách như một nghệ thuật Tóm tắt cuốn sách \"Đọc Sách Như Một Nghệ Thuật\": Đọc sách như một nghệ thuật, ngay từ lần xuất bản đầu tiên năm 1940, đã được đánh giá là cuốn sách hướng dẫn đọc hiểu lý thú và hiệu quả nhất dành cho độc giả phổ thông. Cuốn sách đã nhanh chóng trở thành một tác phẩm kinh điển về cách đọc sách thông minh.\nĐọc sách như một nghệ thuật giúp bạn khám phá và lĩnh hội các cấp độ đọc khác nhau, từ đọc sơ cấp, đọc lướt có hệ thống đến đọc kiểm soát và đọc siêu tốc. Bạn có thể áp dụng các cấp độ này cho việc phân loại, chụp X-quang hay phê bình sách, tuỳ theo nhu cầu và mục đích của mình. Nhờ các kỹ năng đọc được hệ thống ở đây, bạn sẽ biết cách tiếp cận và nắm bắt tất cả các loại văn bản, dù đó là sách thực hành, khoa học, toán học, triết học, lịch sử hay các tác phẩm văn học.\nĐọc sách như một nghệ thuật, hơn hết, thúc đẩy ta trở thành độc giả say mê. Cuốn sách là người bạn đường không thể thiếu của mỗi người trên hành trình đối thoại để học hỏi, khám phá, tu thân và trưởng thành, như Decartes đã nói: \"Đọc sách là được trò chuyện với những người thành đạt nhất của các thế kỷ đã qua\".\nMời các bạn đón đọc cuốn sách \"Đọc Sách Như Một Nghệ Thuật - Mortimer J.Adler\"", "detailLink": "https://waka.vn/doc-sach-nhu-mot-nghe-thuat-r6oWLW.html?type=1", "thumpnail": "https://307a0e78.vws.vegacdn.vn/view/v2/image/img.book/0/0/0/4261.jpg?v=2&w=200&h=292"}