{"title": "Mùa thu Đức 1989.", "content": "Mùa thu Đức 1989. Egon Krenz Mùa thu Đức 1989. Tóm tắt cuốn sách \"Mùa Thu Đức 1989\": Những chuyến bay đối ngoại, những cuộc điện thoại và họp bàn với Gorbachev, các tính toán, kế hoạch và tâm niệm \"không bao giờ có chiến tranh khởi phát từ đất Đức lần nữa\"... đã được kể lại bởi một người trong cuộc từng giữ vị trí quan trọng, để \"ngày 9-11 gần như tình cờ mà trở thành một thời điểm của lịch sử Đức đương đại\".\nEgon Krenz đã thuật lại diễn biến của những tuần lễ và giờ phút căng thẳng hồi ấy, như chính ông đã trải nghiệm: những giây phút quyết định CHDC Đức tồn tại hay không tồn tại.\nTruất quyền Honecker - Cơ hội thay đổi đường lối?\nNiềm tin và lệnh phi bạo lực\nThủ tướng Kohl gửi chủ tịch Hội đồng nhà nước CHDC Đức: \" (...) tôi chúc ông (...) có những quyết định đúng đắn và thành công trong nhiệm vụ quan trọng và rất, rất trọng đại này.\" - Mâu thuẫn giữa lời nói và việc làm\nNụ hôn huynh đệ và tình bằng hữu giữa Gorbachev và Krenz ở Matxcơva - cùng quyết tâm củng cố chủ nghĩa xã hội ở CHDC Đức - Ảo tưởng, chiến thuật hay trò chơi?\nMở biên giới ngày 9/11 - Phỏng đoán và sự thật!\nNhững tuần lễ cuối cùng của một chính đáng tối thượng và ban lãnh đạo.\nThời kỳ sau đó...\nMời các bạn đón đọc cuốn sách \"Mùa Thu Đức 1989 - Egon Krenz\"", "detailLink": "https://waka.vn/mua-thu-duc-1989-rK4nQW.html?type=1", "thumpnail": "https://307a0e78.vws.vegacdn.vn/view/v2/image/img.book/0/0/0/2458.jpg?v=2&w=200&h=292"}