{"title": "Hướng đạo sinh (Tập 1)", "content": "Hướng đạo sinh (Tập 1) Robert Baden - Powell Hướng đạo sinh (Tập 1) Tóm tắt cuốn sách \"Hướng Đạo Sinh (Tập 1)\": Sách cung cấp nhiều ý tưởng cho các nhà giáo dục (ở nhà và ở trường), cho tổ chức Đội Thiếu niên Tiền phong, Đoàn Thanh niên.\nNhư tác giả đã viết trong cuốn sách rằng : Chắc hẳn mọi cậu bé trên đời này đều mong muốn phục vụ đất nước mình theo cách này hay cách khác. Và việc trở thành một Hướng đạo sinh là một trong những cách dễ dàng có thể giúp các cậu bé này thực hiện được điều đó. Với bộ sách Hướng đạo sinh này, các em sẽ được học các kỹ năng sinh tồn sống sót như là làm cách nào có thể tự chăm sóc sức khỏe của mình khi sống ở một nới cách xa cuộc sống của con người, nơi không có bác sĩ, bệnh viên. Với cuốn sách các em sẽ bước vào cuộc phiêu lưu kỳ thú bằng qua những khu rừng rậm hoang dã nhất châu Úc, các em đi từ Trung phi đến Nam phi... Thông qua những câu chuyện có thật, rất sống động này sẽ giúp các em trang bị cho mình những kỹ năng cần thiết cũng như là rèn luyện những phẩm chất tốt đẹp để trở một người công dân có ích và sống có lý tưởng.\nTập 1 tác giả viết về nghệ thuật hướng đạo ngoài trời, sẽ giúp các em học các kỹ năng sinh tồn sống sót như là làm cách nào có thể tự chăm sóc sức khỏe của mình khi sống ở một nới cách xa cuộc sống của con người, nơi không có bác sĩ, bệnh viên.\nMời bạn đón đọc cuốn sách: \"Hướng Đạo Sinh (Tập 1) - Robert Baden - Powel\"", "detailLink": "https://waka.vn/huong-dao-sinh-tap-1-rMMnW.html?type=1", "thumpnail": "https://307a0e78.vws.vegacdn.vn/view/v2/image/img.book/0/0/0/1839.jpg?v=3&w=200&h=292"}